Metadata-Version: 1.2
Name: simple-google-vision
Version: 0.1
Summary: Unofficial helpers for Google Vision
Home-page: https://github.com/robmarkcole/simple-google-vision
Author: Robin Cole
Author-email: robmarkcole@gmail.com
License: Apache License, Version 2.0
Platform: UNKNOWN
Classifier: Intended Audience :: Developers
Classifier: Natural Language :: English
Classifier: Programming Language :: Python
Classifier: Programming Language :: Python :: 3
Requires-Python: >=3.6
